bonsai_ipcc/__init__.py
bonsai_ipcc/_checks.py
bonsai_ipcc/_data.py
bonsai_ipcc/_metadata.py
bonsai_ipcc/_sequence.py
bonsai_ipcc/core.py
bonsai_ipcc/log_setup.py
bonsai_ipcc/sample.py
bonsai_ipcc/uncertainties.py
bonsai_ipcc/agriculture/__init__.py
bonsai_ipcc/agriculture/generic/__init__.py
bonsai_ipcc/agriculture/generic/_data.py
bonsai_ipcc/agriculture/generic/elementary.py
bonsai_ipcc/agriculture/livestock_manure/__init__.py
bonsai_ipcc/agriculture/livestock_manure/_data.py
bonsai_ipcc/agriculture/livestock_manure/elementary.py
bonsai_ipcc/agriculture/livestock_manure/sequence.py
bonsai_ipcc/agriculture/soils/__init__.py
bonsai_ipcc/agriculture/soils/_data.py
bonsai_ipcc/agriculture/soils/elementary.py
bonsai_ipcc/agriculture/soils/sequence.py
bonsai_ipcc/data/concordance_activity.csv
bonsai_ipcc/data/concordance_product.csv
bonsai_ipcc/data/concordance_region.csv
bonsai_ipcc/data/concordance_year.csv
bonsai_ipcc/data/dim_activity.csv
bonsai_ipcc/data/dim_amendment_level.csv
bonsai_ipcc/data/dim_amount_of_addition.csv
bonsai_ipcc/data/dim_climate_zone.csv
bonsai_ipcc/data/dim_compressive_strength.csv
bonsai_ipcc/data/dim_cultivation_type.csv
bonsai_ipcc/data/dim_diet_type.csv
bonsai_ipcc/data/dim_drainage_type.csv
bonsai_ipcc/data/dim_emission.csv
bonsai_ipcc/data/dim_exposure_condition.csv
bonsai_ipcc/data/dim_feeding_situation.csv
bonsai_ipcc/data/dim_furnace_operation_type.csv
bonsai_ipcc/data/dim_income_class.csv
bonsai_ipcc/data/dim_landuse_type.csv
bonsai_ipcc/data/dim_landusechange_type.csv
bonsai_ipcc/data/dim_management_practice.csv
bonsai_ipcc/data/dim_moisture_regime.csv
bonsai_ipcc/data/dim_mortar_type.csv
bonsai_ipcc/data/dim_product.csv
bonsai_ipcc/data/dim_property.csv
bonsai_ipcc/data/dim_region.csv
bonsai_ipcc/data/dim_soil_fertility.csv
bonsai_ipcc/data/dim_soil_type.csv
bonsai_ipcc/data/dim_structure.csv
bonsai_ipcc/data/dim_transfer_coefficient_type.csv
bonsai_ipcc/data/dim_unit.csv
bonsai_ipcc/data/dim_waste_moisture.csv
bonsai_ipcc-0.5.3.dist-info/licenses/LICENSE.md
bonsai_ipcc-0.5.3.dist-info/METADATA
bonsai_ipcc-0.5.3.dist-info/WHEEL
bonsai_ipcc-0.5.3.dist-info/top_level.txt
bonsai_ipcc-0.5.3.dist-info/RECORD
