Metadata-Version: 2.4
Name: bonsai_ipcc
Version: 0.5.3
Summary: Implementation of the IPCC Guidelines for National GHG Inventories.
Home-page: https://gitlab.com/bonsamurais/bonsai/util/ipcc
Author: Maik Budzinski
Author-email: maikb@plan.aau.dk
License: MIT
Project-URL: Documentation, https://bonsamurais.gitlab.io/bonsai/util/ipcc
Platform: any
Classifier: Development Status :: 4 - Beta
Classifier: Programming Language :: Python
License-File: LICENSE.md
Requires-Dist: importlib-metadata>=6.6; python_version < "3.8"
Requires-Dist: pandas>=1.5
Requires-Dist: scipy>=1.11
Requires-Dist: uncertainties>=3.1
Requires-Dist: frictionless>=5.13
Requires-Dist: fitter>=1.7.0
Requires-Dist: bonsai_dataio
Provides-Extra: testing
Requires-Dist: setuptools>=61.2; extra == "testing"
Requires-Dist: pytest==7.1; extra == "testing"
Requires-Dist: black>=22.10; extra == "testing"
Requires-Dist: pytest-black>=0.3; extra == "testing"
Requires-Dist: pytest-cov>=3.0; extra == "testing"
Requires-Dist: isort>=5.12; extra == "testing"
Requires-Dist: openpyxl>=3.0; extra == "testing"
Requires-Dist: anytree; extra == "testing"
Dynamic: license-file
